{
    "status": "success",
    "msg": "获取成功",
    "data": [
        {
            "id": "25",
            "subject": "作为一名帅哥，那不是我的目标",
            "create_time": "2015-04-24 11:30",
            "status": 0,
            "intro": "作为一名帅哥，那不是我的目标，我要努力做一个IT技术大咖~"
        },
        {
            "id": "25",
            "subject": "作为一名帅哥，那不是我的目标",
            "create_time": "2015-04-24 11:30",
            "status": 1,
            "intro": "作为一名帅哥，那不是我的目标，我要努力做一个IT技术大咖~"
        },
        {
            "id": "25",
            "subject": "作为一名帅哥，那不是我的目标",
            "create_time": "2015-04-24 11:30",
            "status": 1,
            "intro": "作为一名帅哥，那不是我的目标，我要努力做一个IT技术大咖~"
        },
        {
            "id": "25",
            "subject": "作为一名帅哥，那不是我的目标",
            "create_time": "2015-04-24 11:30",
            "status": 1,
            "intro": "作为一名帅哥，那不是我的目标，我要努力做一个IT技术大咖~"
        },
        {
            "id": "25",
            "subject": "作为一名帅哥，那不是我的目标",
            "create_time": "2015-04-24 11:30",
            "status": 1,
            "intro": "作为一名帅哥，那不是我的目标，我要努力做一个IT技术大咖~"
        },
        {
            "id": "25",
            "subject": "作为一名帅哥，那不是我的目标",
            "create_time": "2015-04-24 11:30",
            "status": 1,
            "intro": "作为一名帅哥，那不是我的目标，我要努力做一个IT技术大咖~"
        },
        {
            "id": "25",
            "subject": "作为一名帅哥，那不是我的目标",
            "create_time": "2015-04-24 11:30",
            "status": 1,
            "intro": "作为一名帅哥，那不是我的目标，我要努力做一个IT技术大咖~"
        },
        {
            "id": "25",
            "subject": "作为一名帅哥，那不是我的目标",
            "create_time": "2015-04-24 11:30",
            "status": 0,
            "intro": "作为一名帅哥，那不是我的目标，我要努力做一个IT技术大咖~"
        },
        {
            "id": "25",
            "subject": "作为一名帅哥，那不是我的目标",
            "create_time": "2015-04-24 11:30",
            "status": 1,
            "intro": "作为一名帅哥，那不是我的目标，我要努力做一个IT技术大咖~"
        },
        {
            "id": "25",
            "subject": "作为一名帅哥，那不是我的目标",
            "create_time": "2015-04-24 11:30",
            "status": 1,
            "intro": "作为一名帅哥，那不是我的目标，我要努力做一个IT技术大咖~"
        },
        {
            "id": "25",
            "subject": "作为一名帅哥，那不是我的目标",
            "create_time": "2015-04-24 11:30",
            "status": 1,
            "intro": "作为一名帅哥，那不是我的目标，我要努力做一个IT技术大咖~"
        },
        {
            "id": "25",
            "subject": "作为一名帅哥，那不是我的目标",
            "create_time": "2015-04-24 11:30",
            "status": 1,
            "intro": "作为一名帅哥，那不是我的目标，我要努力做一个IT技术大咖~"
        },
        {
            "id": "25",
            "subject": "作为一名帅哥，那不是我的目标",
            "create_time": "2015-04-24 11:30",
            "status": 0,
            "intro": "作为一名帅哥，那不是我的目标，我要努力做一个IT技术大咖~"
        }
    ],
    "referer": "",
    "state": "success"
}